LICENSE
README.md
setup.cfg
setup.py
django_easy_notify.egg-info/PKG-INFO
django_easy_notify.egg-info/SOURCES.txt
django_easy_notify.egg-info/dependency_links.txt
django_easy_notify.egg-info/requires.txt
django_easy_notify.egg-info/top_level.txt
django_notifications/__init__.py
django_notifications/asgi.py
django_notifications/settings.py
django_notifications/test_settings.py
django_notifications/urls.py
django_notifications/wsgi.py
notifications/__init__.py
notifications/admin.py
notifications/apps.py
notifications/consumers.py
notifications/models.py
notifications/routing.py
notifications/urls.py
notifications/utils.py
notifications/views.py
notifications/migrations/0001_initial.py
notifications/migrations/0002_alter_notification_state.py
notifications/migrations/__init__.py